pytest_requires.py
pytest_requires-0.1.0.dist-info/LICENSE
pytest_requires-0.1.0.dist-info/METADATA
pytest_requires-0.1.0.dist-info/WHEEL
pytest_requires-0.1.0.dist-info/entry_points.txt
pytest_requires-0.1.0.dist-info/top_level.txt
pytest_requires-0.1.0.dist-info/RECORD
