Metadata-Version: 2.1
Name: pytest-requires
Version: 0.1.0
Summary: A pytest plugin to elegantly skip tests with optional requirements
Home-page: https://github.com/duncanmmacleod/pytest-requires
Author: Duncan Macleod
Author-email: duncanmmacleod@gmail.com
Maintainer: Duncan Macleod
Maintainer-email: duncanmmacleod@gmail.com
License: MIT
Project-URL: Bug Tracker, https://github.com/duncanmmacleod/pytest-requires/issues
Project-URL: Source Code, https://github.com/duncanmmacleod/pytest-requires
Platform: UNKNOWN
Classifier: Development Status :: 4 - Beta
Classifier: Framework :: Pytest
Classifier: Intended Audience :: Developers
Classifier: License :: OSI Approved :: MIT License
Classifier: Operating System :: OS Independent
Classifier: Programming Language :: Python
Classifier: Programming Language :: Python :: 3
Classifier: Programming Language :: Python :: 3.7
Classifier: Programming Language :: Python :: 3.8
Classifier: Programming Language :: Python :: 3.9
Classifier: Programming Language :: Python :: 3.10
Classifier: Programming Language :: Python :: 3 :: Only
Classifier: Topic :: Software Development :: Testing
Requires-Python: >=3.5
License-File: LICENSE
Requires-Dist: pytest (>=3.5.0)
